heureka_overene/__init__.py
heureka_overene/certification.py
heureka_overene/const.py
heureka_overene/request.py
heureka_overene/utils.py
heureka_overene-0.0.3.dist-info/LICENSE
heureka_overene-0.0.3.dist-info/METADATA
heureka_overene-0.0.3.dist-info/WHEEL
heureka_overene-0.0.3.dist-info/top_level.txt
heureka_overene-0.0.3.dist-info/RECORD
