Metadata-Version: 2.1
Name: heureka-overene
Version: 0.0.3
Summary: Heureka API client for service overene zákazníkmi
Home-page: https://github.com/wisdom-technologies/heureka-overene
Author: Michal Kubek
Author-email: kubek@wisdomtech.sk
License: UNKNOWN
Project-URL: Bug Tracker, https://github.com/wisdom-technologies/heureka-overene/issues
Platform: UNKNOWN
Classifier: Programming Language :: Python :: 3
Classifier: License :: OSI Approved :: MIT License
Classifier: Operating System :: OS Independent
Requires-Python: >=3.6
Requires-Dist: requests
Provides-Extra: test
Requires-Dist: httpretty ; extra == 'test'
Requires-Dist: pytest ; extra == 'test'
